django_timed_tests/__init__.py
django_timed_tests/runner.py
django_timed_tests-0.1.4.dist-info/LICENSE
django_timed_tests-0.1.4.dist-info/METADATA
django_timed_tests-0.1.4.dist-info/WHEEL
django_timed_tests-0.1.4.dist-info/top_level.txt
django_timed_tests-0.1.4.dist-info/RECORD
